{
    "id": "Lair_of_Tarn_Razorlor",
    "name": "Lair of Tarn Razorlor",
    "members": true,
    "type": "Miniquest",
    "difficulty": "Experienced",
    "length": "Medium (Very Short if using a Slayer ring to get to Tarn's Lair)",
    "series": null,
    "description": "This miniquest is to kill Tarn Razorlor and retrieve his diary. Using his diary on a salve amulet will enchant it increasing its attack and strength bonuses by 5%.",
    "start_point": null,
    "image": "https://oldschool.runescape.wiki/w/File:Lair_of_Tarn_Razorlor.png",
    "wiki_url": "https://oldschool.runescape.wiki/w/Lair_of_Tarn_Razorlor",
    "wiki_quick_guide_url": null,
    "developer": null,
    "release_date": "2007-01-22",
    "required_for_completing": null,
    "requirements": {
        "quest_points": null,
        "skills": [
            {
                "name": "Slayer",
                "level": 40
            }
        ],
        "items": null,
        "quests": [
            "Haunted Mine"
        ],
        "misc": null
    },
    "recommended_requirements": null,
    "rewards": null
}